MANIFEST.in
setup.py
bin/cpu_env.sh
bin/gpu_env.sh
bin/monitor_gpu_status.sh
deepy/__init__.py
deepy/__init__.pyc
deepy.egg-info/PKG-INFO
deepy.egg-info/SOURCES.txt
deepy.egg-info/dependency_links.txt
deepy.egg-info/requires.txt
deepy.egg-info/top_level.txt
deepy/conf/__init__.py
deepy/conf/__init__.pyc
deepy/conf/config.py
deepy/conf/config.pyc
deepy/conf/trainer_config.py
deepy/conf/trainer_config.pyc
deepy/dataset/__init__.py
deepy/dataset/__init__.pyc
deepy/dataset/basic.py
deepy/dataset/basic.pyc
deepy/dataset/binarized_mnist.py
deepy/dataset/binarized_mnist.pyc
deepy/dataset/bunch_seq.py
deepy/dataset/bunch_seq.pyc
deepy/dataset/dataset.py
deepy/dataset/dataset.pyc
deepy/dataset/mini_batch.py
deepy/dataset/mini_batch.pyc
deepy/dataset/mnist.py
deepy/dataset/mnist.pyc
deepy/dataset/ondisk_dataset.py
deepy/dataset/ondisk_dataset.pyc
deepy/dataset/padding.py
deepy/dataset/padding.pyc
deepy/dataset/seq_mini_batch.py
deepy/dataset/seq_mini_batch.pyc
deepy/dataset/sequence.py
deepy/dataset/sequence.pyc
deepy/layers/__init__.py
deepy/layers/__init__.pyc
deepy/layers/activation.py
deepy/layers/activation.pyc
deepy/layers/batch_norm.py
deepy/layers/batch_norm.pyc
deepy/layers/bias.py
deepy/layers/bias.pyc
deepy/layers/block.py
deepy/layers/block.pyc
deepy/layers/chain.py
deepy/layers/chain.pyc
deepy/layers/combine.py
deepy/layers/combine.pyc
deepy/layers/concatenate.py
deepy/layers/concatenate.pyc
deepy/layers/conv.py
deepy/layers/conv.pyc
deepy/layers/dense.py
deepy/layers/dense.pyc
deepy/layers/dimshuffle.py
deepy/layers/dimshuffle.pyc
deepy/layers/dropout.py
deepy/layers/dropout.pyc
deepy/layers/flatten.py
deepy/layers/flatten.pyc
deepy/layers/gru.py
deepy/layers/gru.pyc
deepy/layers/irnn.py
deepy/layers/irnn.pyc
deepy/layers/layer.py
deepy/layers/layer.pyc
deepy/layers/lstm.py
deepy/layers/lstm.pyc
deepy/layers/maxout.py
deepy/layers/maxout.pyc
deepy/layers/onehot_embed.py
deepy/layers/onehot_embed.pyc
deepy/layers/prelu.py
deepy/layers/prelu.pyc
deepy/layers/recurrent.py
deepy/layers/recurrent.pyc
deepy/layers/reshape.py
deepy/layers/reshape.pyc
deepy/layers/reveal_dimension.py
