Metadata-Version: 1.1
Name: deepy
Version: 0.2.1
Summary: Highly extensible deep learning framework based on Theano
Home-page: https://github.com/uaca/deepy
Author: Raphael Shu
Author-email: raphael@uaca.com
License: MIT
Download-URL: http://pypi.python.org/pypi/deepy
Keywords: Deep learning  Neural network  Natural language processing
Platform: any
Classifier: Development Status :: 2 - Pre-Alpha
Classifier: Environment :: Console
Classifier: Intended Audience :: Science/Research
Classifier: License :: OSI Approved :: MIT License
Classifier: Operating System :: OS Independent
Classifier: Programming Language :: Python :: 2.6
Classifier: Programming Language :: Python :: 2.7
Classifier: Topic :: Scientific/Engineering :: Artificial Intelligence
Classifier: Topic :: Scientific/Engineering :: Information Analysis
Classifier: Topic :: Text Processing :: Linguistic
